{"trueAscent":-94.5,"trueDescent":23.5,"glyphs":{"32":{"minX":0,"minY":-5,"maxX":28.100000000000005,"maxY":0,"width":28.100000000000005,"height":5},"33":{"minX":5,"maxX":20,"minY":-70.5,"maxY":0.5,"width":15,"height":71},"34":{"minX":5,"maxX":34,"minY":-70.5,"maxY":-39.5,"width":29,"height":31},"35":{"minX":3,"maxX":51,"minY":-63.5,"maxY":-1.5,"width":48,"height":62},"36":{"minX":4,"maxX":47,"minY":-67.5,"maxY":-0.5,"width":43,"height":67},"37":{"minX":4,"maxX":66,"minY":-67.5,"maxY":0.5,"width":62,"height":68},"38":{"minX":4,"maxX":69,"minY":-70.5,"maxY":0.5,"width":65,"height":71},"39":{"minX":4,"maxX":16,"minY":-69.5,"maxY":-39.5,"width":12,"height":30},"40":{"minX":8,"maxX":33,"minY":-77.5,"maxY":14.5,"width":25,"height":92},"41":{"minX":4,"maxX":29,"minY":-76.5,"maxY":14.5,"width":25,"height":91},"42":{"minX":3,"maxX":39,"minY":-70.5,"maxY":-35.5,"width":36,"height":35},"43":{"minX":2,"maxX":47,"minY":-53.5,"maxY":-12.5,"width":45,"height":41},"44":{"minX":5,"maxX":20,"minY":-14.5,"maxY":12.5,"width":15,"height":27},"45":{"minX":3,"maxX":34,"minY":-33.5,"maxY":-23.5,"width":31,"height":10},"46":{"minX":4,"maxX":19,"minY":-13.5,"maxY":1.5,"width":15,"height":15},"47":{"minX":1,"maxX":39,"minY":-70.5,"maxY":2.5,"width":38,"height":73},"48":{"minX":5,"maxX":58,"minY":-67.5,"maxY":0.5,"width":53,"height":68},"49":{"minX":2,"maxX":28,"minY":-67.5,"maxY":-0.5,"width":26,"height":67},"50":{"minX":4,"maxX":53,"minY":-67.5,"maxY":0.5,"width":49,"height":68},"51":{"minX":4,"maxX":54,"minY":-66.5,"maxY":0.5,"width":50,"height":67},"52":{"minX":6,"maxX":54,"minY":-66.5,"maxY":0.5,"width":48,"height":67},"53":{"minX":4,"maxX":54,"minY":-66.5,"maxY":0.5,"width":50,"height":67},"54":{"minX":5,"maxX":55,"minY":-67.5,"maxY":0.5,"width":50,"height":68},"55":{"minX":2,"maxX":48,"minY":-67.5,"maxY":-0.5,"width":46,"height":67},"56":{"minX":5,"maxX":57,"minY":-66.5,"maxY":0.5,"width":52,"height":67},"57":{"minX":4,"maxX":55,"minY":-66.5,"maxY":1.5,"width":51,"height":68},"58":{"minX":5,"maxX":20,"minY":-45.5,"maxY":1.5,"width":15,"height":47},"59":{"minX":4,"maxX":20,"minY":-45.5,"maxY":12.5,"width":16,"height":58},"60":{"minX":2,"maxX":47,"minY":-61.5,"maxY":-7.5,"width":45,"height":54},"61":{"minX":6,"maxX":46,"minY":-48.5,"maxY":-19.5,"width":40,"height":29},"62":{"minX":5,"maxX":50,"minY":-61.5,"maxY":-6.5,"width":45,"height":55},"63":{"minX":2,"maxX":50,"minY":-70.5,"maxY":1.5,"width":48,"height":72},"64":{"minX":4,"maxX":77,"minY":-63.5,"maxY":13.5,"width":73,"height":77},"65":{"minX":1,"maxX":64,"minY":-70.5,"maxY":0.5,"width":63,"height":71},"66":{"minX":6,"maxX":60,"minY":-69.5,"maxY":-0.5,"width":54,"height":69},"67":{"minX":4,"maxX":67,"minY":-70.5,"maxY":0.5,"width":63,"height":71},"68":{"minX":6,"maxX":62,"minY":-69.5,"maxY":-0.5,"width":56,"height":69},"69":{"minX":6,"maxX":52,"minY":-69.5,"maxY":-0.5,"width":46,"height":69},"70":{"minX":6,"maxX":52,"minY":-69.5,"maxY":-1.5,"width":46,"height":68},"71":{"minX":5,"maxX":67,"minY":-71.5,"maxY":1.5,"width":62,"height":73},"72":{"minX":6,"maxX":60,"minY":-69.5,"maxY":-0.5,"width":54,"height":69},"73":{"minX":2,"maxX":37,"minY":-70.5,"maxY":-0.5,"width":35,"height":70},"74":{"minX":1,"maxX":57,"minY":-69.5,"maxY":0.5,"width":56,"height":70},"75":{"minX":6,"maxX":64,"minY":-69.5,"maxY":1.5,"width":58,"height":71},"76":{"minX":6,"maxX":51,"minY":-69.5,"maxY":-0.5,"width":45,"height":69},"77":{"minX":5,"maxX":76,"minY":-69.5,"maxY":-0.5,"width":71,"height":69},"78":{"minX":6,"maxX":60,"minY":-70.5,"maxY":0.5,"width":54,"height":71},"79":{"minX":4,"maxX":70,"minY":-71.5,"maxY":0.5,"width":66,"height":72},"80":{"minX":6,"maxX":58,"minY":-69.5,"maxY":-0.5,"width":52,"height":69},"81":{"minX":4,"maxX":70,"minY":-71.5,"maxY":11.5,"width":66,"height":83},"82":{"minX":6,"maxX":58,"minY":-69.5,"maxY":2.5,"width":52,"height":72},"83":{"minX":4,"maxX":58,"minY":-70.5,"maxY":0.5,"width":54,"height":71},"84":{"minX":2,"maxX":58,"minY":-69.5,"maxY":-0.5,"width":56,"height":69},"85":{"minX":5,"maxX":61,"minY":-69.5,"maxY":0.5,"width":56,"height":70},"86":{"minX":1,"maxX":61,"minY":-70.5,"maxY":-0.5,"width":60,"height":70},"87":{"minX":1,"maxX":84,"minY":-69.5,"maxY":-0.5,"width":83,"height":69},"88":{"minX":3,"maxX":64,"minY":-70.5,"maxY":0.5,"width":61,"height":71},"89":{"minX":1,"maxX":61,"minY":-70.5,"maxY":-0.5,"width":60,"height":70},"90":{"minX":4,"maxX":57,"minY":-69.5,"maxY":0.5,"width":53,"height":70},"91":{"minX":8,"maxX":32,"minY":-77.5,"maxY":14.5,"width":24,"height":92},"92":{"minX":2,"maxX":38,"minY":-70.5,"maxY":1.5,"width":36,"height":72},"93":{"minX":3,"maxX":26,"minY":-77.5,"maxY":13.5,"width":23,"height":91},"94":{"minX":3,"maxX":42,"minY":-69.5,"maxY":-34.5,"width":39,"height":35},"95":{"minX":2,"maxX":56,"minY":2.5,"maxY":11.5,"width":54,"height":9},"96":{"minX":3,"maxX":26,"minY":-72.5,"maxY":-56.5,"width":23,"height":16},"97":{"minX":2,"maxX":49,"minY":-48.5,"maxY":0.5,"width":47,"height":49},"98":{"minX":6,"maxX":53,"minY":-72.5,"maxY":1.5,"width":47,"height":74},"99":{"minX":4,"maxX":49,"minY":-47.5,"maxY":1.5,"width":45,"height":49},"100":{"minX":2,"maxX":49,"minY":-72.5,"maxY":1.5,"width":47,"height":74},"101":{"minX":4,"maxX":51,"minY":-47.5,"maxY":0.5,"width":47,"height":48},"102":{"minX":1,"maxX":38,"minY":-75.5,"maxY":-0.5,"width":37,"height":75},"103":{"minX":3,"maxX":50,"minY":-48.5,"maxY":23.5,"width":47,"height":72},"104":{"minX":6,"maxX":47,"minY":-72.5,"maxY":-0.5,"width":41,"height":72},"105":{"minX":5,"maxX":20,"minY":-68.5,"maxY":-0.5,"width":15,"height":68},"106":{"minX":-6,"maxX":24,"minY":-69.5,"maxY":21.5,"width":30,"height":91},"107":{"minX":6,"maxX":51,"minY":-72.5,"maxY":2.5,"width":45,"height":75},"108":{"minX":5,"maxX":18,"minY":-72.5,"maxY":-0.5,"width":13,"height":72},"109":{"minX":6,"maxX":74,"minY":-48.5,"maxY":-0.5,"width":68,"height":48},"110":{"minX":6,"maxX":50,"minY":-47.5,"maxY":-0.5,"width":44,"height":47},"111":{"minX":5,"maxX":54,"minY":-48.5,"maxY":1.5,"width":49,"height":50},"112":{"minX":6,"maxX":53,"minY":-48.5,"maxY":21.5,"width":47,"height":70},"113":{"minX":3,"maxX":66,"minY":-48.5,"maxY":21.5,"width":63,"height":70},"114":{"minX":6,"maxX":42,"minY":-47.5,"maxY":-0.5,"width":36,"height":47},"115":{"minX":3,"maxX":47,"minY":-48.5,"maxY":0.5,"width":44,"height":49},"116":{"minX":1,"maxX":33,"minY":-72.5,"maxY":-0.5,"width":32,"height":72},"117":{"minX":5,"maxX":49,"minY":-47.5,"maxY":0.5,"width":44,"height":48},"118":{"minX":1,"maxX":49,"minY":-47.5,"maxY":-0.5,"width":48,"height":47},"119":{"minX":1,"maxX":77,"minY":-47.5,"maxY":-0.5,"width":76,"height":47},"120":{"minX":4,"maxX":53,"minY":-48.5,"maxY":0.5,"width":49,"height":49},"121":{"minX":1,"maxX":49,"minY":-47.5,"maxY":22.5,"width":48,"height":70},"122":{"minX":4,"maxX":50,"minY":-46.5,"maxY":0.5,"width":46,"height":47},"123":{"minX":6,"maxX":33,"minY":-77.5,"maxY":15.5,"width":27,"height":93},"124":{"minX":6,"maxX":16,"minY":-73.5,"maxY":7.5,"width":10,"height":81},"125":{"minX":4,"maxX":32,"minY":-77.5,"maxY":15.5,"width":28,"height":93},"126":{"minX":4,"maxX":58,"minY":-43.5,"maxY":-26.5,"width":54,"height":17},"161":{"minX":5,"maxX":20,"minY":-57.5,"maxY":13.5,"width":15,"height":71},"162":{"minX":3,"maxX":45,"minY":-67.5,"maxY":-1.5,"width":42,"height":66},"163":{"minX":2,"maxX":55,"minY":-64.5,"maxY":2.5,"width":53,"height":67},"165":{"minX":3,"maxX":59,"minY":-66.5,"maxY":-0.5,"width":56,"height":66},"166":{"minX":5,"maxX":16,"minY":-73.5,"maxY":7.5,"width":11,"height":81},"167":{"minX":5,"maxX":49,"minY":-71.5,"maxY":4.5,"width":44,"height":76},"168":{"minX":5,"maxX":37,"minY":-69.5,"maxY":-57.5,"width":32,"height":12},"170":{"minX":4,"maxX":35,"minY":-68.5,"maxY":-38.5,"width":31,"height":30},"171":{"minX":3,"maxX":51,"minY":-47.5,"maxY":-9.5,"width":48,"height":38},"172":{"minX":5,"maxX":49,"minY":-39.5,"maxY":-12.5,"width":44,"height":27},"175":{"minX":6,"maxX":37,"minY":-66.5,"maxY":-59.5,"width":31,"height":7},"176":{"minX":4,"maxX":40,"minY":-71.5,"maxY":-38.5,"width":36,"height":33},"177":{"minX":2,"maxX":47,"minY":-53.5,"maxY":5.5,"width":45,"height":59},"178":{"minX":7,"maxX":30,"minY":-70.5,"maxY":-40.5,"width":23,"height":30},"179":{"minX":7,"maxX":30,"minY":-70.5,"maxY":-39.5,"width":23,"height":31},"180":{"minX":3,"maxX":28,"minY":-72.5,"maxY":-55.5,"width":25,"height":17},"181":{"minX":5,"maxX":53,"minY":-47.5,"maxY":21.5,"width":48,"height":69},"182":{"minX":4,"maxX":58,"minY":-71.5,"maxY":14.5,"width":54,"height":86},"183":{"minX":5,"maxX":37,"minY":-50.5,"maxY":-18.5,"width":32,"height":32},"184":{"minX":3,"maxX":19,"minY":-1.5,"maxY":20.5,"width":16,"height":22},"185":{"minX":11,"maxX":24,"minY":-71.5,"maxY":-40.5,"width":13,"height":31},"186":{"minX":5,"maxX":35,"minY":-68.5,"maxY":-37.5,"width":30,"height":31},"187":{"minX":5,"maxX":53,"minY":-47.5,"maxY":-9.5,"width":48,"height":38},"188":{"minX":2,"maxX":34,"minY":-71.5,"maxY":6.5,"width":32,"height":78},"189":{"minX":2,"maxX":34,"minY":-71.5,"maxY":6.5,"width":32,"height":78},"190":{"minX":2,"maxX":34,"minY":-70.5,"maxY":6.5,"width":32,"height":77},"191":{"minX":1,"maxX":48,"minY":-57.5,"maxY":14.5,"width":47,"height":72},"192":{"minX":1,"maxX":64,"minY":-93.5,"maxY":0.5,"width":63,"height":94},"193":{"minX":1,"maxX":64,"minY":-93.5,"maxY":0.5,"width":63,"height":94},"194":{"minX":1,"maxX":64,"minY":-93.5,"maxY":0.5,"width":63,"height":94},"195":{"minX":1,"maxX":64,"minY":-91.5,"maxY":0.5,"width":63,"height":92},"196":{"minX":1,"maxX":64,"minY":-90.5,"maxY":0.5,"width":63,"height":91},"197":{"minX":1,"maxX":64,"minY":-94.5,"maxY":0.5,"width":63,"height":95},"198":{"minX":1,"maxX":83,"minY":-70.5,"maxY":0.5,"width":82,"height":71},"199":{"minX":4,"maxX":67,"minY":-70.5,"maxY":20.5,"width":63,"height":91},"200":{"minX":6,"maxX":52,"minY":-93.5,"maxY":-0.5,"width":46,"height":93},"201":{"minX":6,"maxX":52,"minY":-93.5,"maxY":-0.5,"width":46,"height":93},"202":{"minX":6,"maxX":52,"minY":-93.5,"maxY":-0.5,"width":46,"height":93},"203":{"minX":6,"maxX":52,"minY":-90.5,"maxY":-0.5,"width":46,"height":90},"204":{"minX":2,"maxX":37,"minY":-93.5,"maxY":-0.5,"width":35,"height":93},"205":{"minX":2,"maxX":37,"minY":-93.5,"maxY":-0.5,"width":35,"height":93},"206":{"minX":2,"maxX":37,"minY":-93.5,"maxY":-0.5,"width":35,"height":93},"207":{"minX":2,"maxX":37,"minY":-90.5,"maxY":-0.5,"width":35,"height":90},"208":{"minX":2,"maxX":64,"minY":-69.5,"maxY":-0.5,"width":62,"height":69},"209":{"minX":6,"maxX":60,"minY":-91.5,"maxY":0.5,"width":54,"height":92},"210":{"minX":4,"maxX":70,"minY":-93.5,"maxY":0.5,"width":66,"height":94},"211":{"minX":4,"maxX":70,"minY":-93.5,"maxY":0.5,"width":66,"height":94},"212":{"minX":4,"maxX":70,"minY":-93.5,"maxY":0.5,"width":66,"height":94},"213":{"minX":4,"maxX":70,"minY":-91.5,"maxY":0.5,"width":66,"height":92},"214":{"minX":4,"maxX":70,"minY":-90.5,"maxY":0.5,"width":66,"height":91},"215":{"minX":5,"maxX":43,"minY":-52.5,"maxY":-14.5,"width":38,"height":38},"216":{"minX":4,"maxX":70,"minY":-74.5,"maxY":5.5,"width":66,"height":80},"217":{"minX":5,"maxX":61,"minY":-93.5,"maxY":0.5,"width":56,"height":94},"218":{"minX":5,"maxX":61,"minY":-93.5,"maxY":0.5,"width":56,"height":94},"219":{"minX":5,"maxX":61,"minY":-93.5,"maxY":0.5,"width":56,"height":94},"220":{"minX":5,"maxX":61,"minY":-90.5,"maxY":0.5,"width":56,"height":91},"221":{"minX":1,"maxX":61,"minY":-93.5,"maxY":-0.5,"width":60,"height":93},"223":{"minX":6,"maxX":51,"minY":-71.5,"maxY":0.5,"width":45,"height":72},"224":{"minX":2,"maxX":49,"minY":-72.5,"maxY":0.5,"width":47,"height":73},"225":{"minX":2,"maxX":49,"minY":-72.5,"maxY":0.5,"width":47,"height":73},"226":{"minX":2,"maxX":49,"minY":-72.5,"maxY":0.5,"width":47,"height":73},"227":{"minX":2,"maxX":49,"minY":-71.5,"maxY":0.5,"width":47,"height":72},"228":{"minX":2,"maxX":49,"minY":-69.5,"maxY":0.5,"width":47,"height":70},"229":{"minX":2,"maxX":49,"minY":-74.5,"maxY":0.5,"width":47,"height":75},"230":{"minX":4,"maxX":84,"minY":-48.5,"maxY":0.5,"width":80,"height":49},"231":{"minX":4,"maxX":49,"minY":-47.5,"maxY":20.5,"width":45,"height":68},"232":{"minX":4,"maxX":51,"minY":-72.5,"maxY":0.5,"width":47,"height":73},"233":{"minX":4,"maxX":51,"minY":-72.5,"maxY":0.5,"width":47,"height":73},"234":{"minX":4,"maxX":51,"minY":-72.5,"maxY":0.5,"width":47,"height":73},"235":{"minX":4,"maxX":51,"minY":-69.5,"maxY":0.5,"width":47,"height":70},"236":{"minX":-2,"maxX":21,"minY":-72.5,"maxY":-0.5,"width":23,"height":72},"237":{"minX":3,"maxX":28,"minY":-72.5,"maxY":-0.5,"width":25,"height":72},"238":{"minX":-3,"maxX":28,"minY":-72.5,"maxY":-0.5,"width":31,"height":72},"239":{"minX":-4,"maxX":28,"minY":-69.5,"maxY":-0.5,"width":32,"height":69},"240":{"minX":3,"maxX":51,"minY":-72.5,"maxY":1.5,"width":48,"height":74},"241":{"minX":6,"maxX":50,"minY":-71.5,"maxY":-0.5,"width":44,"height":71},"242":{"minX":5,"maxX":54,"minY":-72.5,"maxY":1.5,"width":49,"height":74},"243":{"minX":5,"maxX":54,"minY":-72.5,"maxY":1.5,"width":49,"height":74},"244":{"minX":5,"maxX":54,"minY":-72.5,"maxY":1.5,"width":49,"height":74},"245":{"minX":5,"maxX":54,"minY":-71.5,"maxY":1.5,"width":49,"height":73},"246":{"minX":5,"maxX":54,"minY":-69.5,"maxY":1.5,"width":49,"height":71},"247":{"minX":2,"maxX":48,"minY":-60.5,"maxY":-8.5,"width":46,"height":52},"248":{"minX":4,"maxX":54,"minY":-53.5,"maxY":5.5,"width":50,"height":59},"249":{"minX":5,"maxX":49,"minY":-72.5,"maxY":0.5,"width":44,"height":73},"250":{"minX":5,"maxX":49,"minY":-72.5,"maxY":0.5,"width":44,"height":73},"251":{"minX":5,"maxX":49,"minY":-72.5,"maxY":0.5,"width":44,"height":73},"252":{"minX":5,"maxX":49,"minY":-69.5,"maxY":0.5,"width":44,"height":70},"253":{"minX":1,"maxX":49,"minY":-72.5,"maxY":22.5,"width":48,"height":95},"254":{"minX":6,"maxX":52,"minY":-72.5,"maxY":21.5,"width":46,"height":94},"255":{"minX":1,"maxX":49,"minY":-69.5,"maxY":22.5,"width":48,"height":92},"8211":{"minX":2,"maxX":61,"minY":-33.5,"maxY":-22.5,"width":59,"height":11},"8212":{"minX":2,"maxX":100,"minY":-33.5,"maxY":-22.5,"width":98,"height":11},"8216":{"minX":4,"maxX":19,"minY":-74.5,"maxY":-47.5,"width":15,"height":27},"8217":{"minX":5,"maxX":20,"minY":-72.5,"maxY":-45.5,"width":15,"height":27},"8218":{"minX":4,"maxX":20,"minY":-13.5,"maxY":13.5,"width":16,"height":27},"8220":{"minX":5,"maxX":39,"minY":-74.5,"maxY":-47.5,"width":34,"height":27},"8221":{"minX":5,"maxX":40,"minY":-72.5,"maxY":-45.5,"width":35,"height":27},"8222":{"minX":5,"maxX":40,"minY":-13.5,"maxY":13.5,"width":35,"height":27},"8224":{"minX":2,"maxX":40,"minY":-69.5,"maxY":-4.5,"width":38,"height":65},"8225":{"minX":2,"maxX":40,"minY":-69.5,"maxY":-3.5,"width":38,"height":66},"8226":{"minX":5,"maxX":37,"minY":-50.5,"maxY":-18.5,"width":32,"height":32},"8230":{"minX":6,"maxX":81,"minY":-13.5,"maxY":1.5,"width":75,"height":15},"8240":{"minX":5,"maxX":79,"minY":-67.5,"maxY":-0.5,"width":74,"height":67},"8729":{"minX":5,"maxX":37,"minY":-50.5,"maxY":-18.5,"width":32,"height":32},"9675":{"minX":5,"maxX":37,"minY":-50.5,"maxY":-18.5,"width":32,"height":32},"9679":{"minX":5,"maxX":37,"minY":-50.5,"maxY":-18.5,"width":32,"height":32},"9702":{"minX":5,"maxX":37,"minY":-50.5,"maxY":-18.5,"width":32,"height":32},"12539":{"minX":5,"maxX":37,"minY":-50.5,"maxY":-18.5,"width":32,"height":32}}}
